[{"T15326594190002742":[{"dj_input":"Y","dj_remark":"","dj_select":"w_close","dj_textarea":"","dqkj":"botton_1532659433848","hqgb_input":"","hqgb_remark":"","hqgb_select":"s_true","hqgb_textarea":"","id":"botton_1532659433848","sj_input":"","sj_remark":"","sj_select":"s_true","sj_textarea":"","sjgg_input":"","sjgg_remark":"","sjgg_select":"","sjgg_textarea":"","sqgb_input":"","sqgb_remark":"","sqgb_select":"s_true","sqgb_textarea":""},{"dj_input":"Y","dj_remark":"","dj_select":"s_true","dj_textarea":"alert(1);","dqkj":"botton_1532659429078","hqgb_input":"","hqgb_remark":"","hqgb_select":"s_true","hqgb_textarea":"","id":"botton_1532659429078","sj_input":"","sj_remark":"","sj_select":"s_true","sj_textarea":"","sjgg_input":"","sjgg_remark":"","sjgg_select":"","sjgg_textarea":"","sqgb_input":"","sqgb_remark":"","sqgb_select":"s_true","sqgb_textarea":""}]}]